tym/__init__.py
tym/adapter.py
tym/commands/__init__.py
tym/commands/init.py
tym/commands/login.py
tym/commands/logout.py
tym/commands/share.py
tym/commands/start.py
tym/commands/uninit.py
tym/commons.py
tym/config_parser/__init__.py
tym/config_parser/authentication.py
tym/config_parser/repo.py
tym/constants.py
tym/git_helpers.py
tym/main.py
tym/models.py
tym/server.py
tym-0.1.1.dist-info/entry_points.txt
tym-0.1.1.dist-info/WHEEL
tym-0.1.1.dist-info/METADATA
tym-0.1.1.dist-info/RECORD
