Metadata-Version: 2.1
Name: tym
Version: 0.1.1
Summary: 
Author: Tym
Author-email: dev@tym.so
Requires-Python: >=3.6,<4.0
Classifier: Programming Language :: Python :: 3
Classifier: Programming Language :: Python :: 3.6
Classifier: Programming Language :: Python :: 3.7
Classifier: Programming Language :: Python :: 3.8
Classifier: Programming Language :: Python :: 3.9
Requires-Dist: aiodns (>=3.0.0,<4.0.0)
Requires-Dist: aiohttp (>=3.7.4,<4.0.0)
Requires-Dist: aiohttp_cors (>=0.7.0,<0.8.0)
Requires-Dist: cached-property (>=1.5.2,<2.0.0)
Requires-Dist: cchardet (>=2.1.7,<3.0.0)
Requires-Dist: pygit2 (>=1.6.1,<2.0.0)
Requires-Dist: simple-term-menu (>=1.2.1,<2.0.0)
Requires-Dist: typer[all] (>=0.3.2,<0.4.0)
Requires-Dist: watchgod (>=0.7,<0.8)
